{"h":[{"d":[{"f":"`指~`人~`擁有~`的~`七~`種~`感情~，`即~`喜~、`怒~、`哀~、`懼~、`愛~、`惡~、`慾~。"},{"f":"`中醫~`指~`喜~、`怒~、`憂~、`思~、`悲~、`恐~、`驚~`等~`七~`種~`情緒~`狀態~，`若~`七情~`太~`過~，`則~`會~`成為~`內傷~`的~`病因~。"}],"_":"1000030051","p":"qīqíng","b":"ㄑㄧ　ㄑㄧㄥˊ"}],"translation":{"Deutsch":["die sieben menschlichen Gemütsregungen (Freude, Zorn, Trauer, Angst, Liebe, Haß, Begehren) "],"English":["seven emotional states","seven affects of traditional Chinese medical theory and therapy, namely: joy `喜~[xi3], anger `怒~[nu4], anxiety `憂~|忧[you1], thought `思~[si1], grief `悲~[bei1], fear `恐~[kong3], fright `驚~|惊[jing1]","seven relations"]},"t":"`七~`情~"}