{"t":"`世~`界~","h":[{"d":[{"e":["例⃝「`世界觀~」。"],"f":"`自然界~`和~`人類~`社會~`的~`總稱~。"},{"e":["例⃝「`世界~`村~」、「`世界~`經濟~」。"],"f":"`地球~`上~`所有~`的~`地方~`或~`國家~。"},{"e":["例⃝「`現在~`是~`什麼~`世界~`了~，`由得~`你~`胡作非為~？」。"],"f":"`指~`社會~`的~`環境~、`狀況~。"},{"e":["例⃝「`兒童~`世界~」、「`內心~`世界~」。"],"f":"`指~`自成體系~`的~`組織~、`現象~`或~`某~`種~`領域~。"},{"e":["例⃝「`大千世界~」。"],"f":"`佛教~`特指~`宇宙~，`表~`無限~`的~`空間~`與~`時間~。"}],"_":"1000120025","p":"shìjiè","b":"ㄕˋ　ㄐㄧㄝˋ"}],"translation":{"francais":["monde (univers)"],"Deutsch":["Universum (S)","Welt (S)","universal (Adj)","weltlich (Adj)","loka (Sanskrit) (S)"],"English":["world","CL:`個~|个[ge4]"]}}