{"n":1,"t":"乃","r":"`丿~","c":2,"h":[{"d":[{"e":["例⃝「`此~`乃~`英雄~`好漢~」、「`失敗~`乃~`成功~`之~`母~」。"],"f":"`是~。"},{"e":["例⃝「`王師~`北~`定~`中原~`日~，`家祭~`無~`忘~`告~`乃翁~`（~`宋~‧`陸~`游~〈`示~`兒~`詩~〉）」。"],"f":"〈`書~〉`你~；`你~`的~。"},{"e":["例⃝「`侯~`生~`視~`公子~`色~`終~`不~`變~，`乃~`謝客~`就~`車~`（~《`史記~‧`卷~`七~`十~`七~‧`魏~`公子~`列傳~》）」。"],"f":"〈`書~〉`於是~。"},{"e":["例⃝「`是~`月~`也~，`日夜~`分~，`雷~`乃~`發聲~`（~《`禮記~‧`月~`令~》）」。"],"f":"〈`書~〉`才~。"},{"e":["例⃝「`問~`今~`是~`何~`世~，`乃~`不~`知~`有~`漢~，`無論~`魏~`晉~`（~`晉~‧`陶~`淵~`明~〈`桃花源~`記~〉）」。"],"f":"〈`書~〉`竟然~；`居然~。"},{"f":"`姓~。"}],"_":"1000260000","p":"nǎi","b":"ㄋㄞˇ"}],"translation":{"Deutsch":["mithin ","sein, lauten "],"English":["to be","thus","so","therefore","then","only","thereupon"]}}