{"t":"`人~`道~","h":[{"d":[{"e":["例⃝「`人道~`救援~」、「`人道~`醫療~」。"],"f":"`尊重~`人類~`生命~`與~`價值~，`強調~`博愛~、`正義~`等~`道德~`理念~`與~`行為~。"},{"e":["例⃝「`不能~`人道~」。"],"f":"`男女~`間~`的~`性行為~。"},{"f":"`指~`人類~。`佛教~`認為~`未~`解脫~`的~`眾生~，`會~`在~`六道~`（~`天~、`人~、`阿~`修~`羅~、`地獄~、`餓鬼~、`畜生~）`中~`不斷~`輪迴~，`人道~`為~`六道~`之~`一~。`也~`作~「`人間道~」。"},{"e":["例⃝「`敬畏~`天~`威~，`遵循~`人道~」。"],"f":"〈`書~〉`人~`應~`遵循~`的~`道理~、`人倫~。"}],"_":"1000680294","p":"réndào","b":"ㄖㄣˊ　ㄉㄠˋ"}],"translation":{"francais":["humain","humanité"],"Deutsch":["Menschlichkeit (S)","menschlich (Adj)"],"English":["human sympathy","humanitarianism","humane","the \"human way\", one of the stages in the cycle of reincarnation (Buddhism)","sexual intercourse"]}}