{"n":9,"t":"偶","r":"`人~","c":11,"h":[{"d":[{"e":["例⃝「`泥~`偶~」、「`人~`偶~」、「`偶像~」、「`玩偶~」。"],"f":"`用~`泥土~、`木頭~、`金屬~`等~`材料~`製~`成~`的~`人像~。"},{"e":["例⃝「`偶數~」、「`無獨有偶~」。"],"f":"`雙數~；`成~`對~。"},{"e":["例⃝「`佳偶~」、「`怨偶~」、「`喪偶~」。"],"f":"`配偶~；`伴侶~。"},{"e":["例⃝「`偶然~」、「`偶爾~」、「`偶~`或~」、「`偶一為之~」。"],"f":"`碰巧~；`剛好~；`非~`預期~`的~；`非~`經常~`性~`的~。"},{"f":"`姓~。"}],"_":"1002090000","p":"ǒu","b":"ㄡˇ"}],"translation":{"francais":["conjoint","par hasard, rarement, à l'occasion","(utilisé pour dire je ou moi de façon mignonne)"],"English":["accidental","image","pair","mate"]}}