{"h":[{"d":[{"e":["例⃝「`切莫~`衝動~！`你們~`兩虎相鬥，必有一傷~」。"],"f":"〈`諺~〉`兩~`隻~`老虎~`互相~`爭鬥~，`必定~`有~`一~`隻~`受傷~。`比喻~`兩~`股~`勢力~`互~`鬥~，`必~`有~`一方~`受~`到~`損傷~。`也~`作~「`兩虎相爭，必有一傷~」。"}],"A":"两`虎~`相~`斗~，`必~`有~`一~伤","_":"1002840049","p":"liǎnghǔ-xiāngdòu,bìyǒu-yìshāng<br>陸⃝liǎnghǔ-xiāngdòu,bìyǒu-yīshāng","b":"ㄌㄧㄤˇ　ㄏㄨˇ　ㄒㄧㄤ　ㄉㄡˋ，ㄅㄧˋ　ㄧㄡˇ　ㄧˋ　ㄕㄤ<br>陸⃝ㄌㄧㄤˇ　ㄏㄨˇ　ㄒㄧㄤ　ㄉㄡˋ，ㄅㄧˋ　ㄧㄡˇ　ㄧ　ㄕㄤ"}],"translation":{"English":["When two tigers fight, one will get injured (idiom). If it comes to a fight, someone will get hurt."]},"t":"`兩虎相鬥~，`必~`有~`一~`傷~"}