{"n":4,"t":"匡","r":"`匚~","c":6,"h":[{"d":[{"e":["例⃝「`匡謬~」、「`匡正~」、「`匡~`過~」。"],"f":"`改正~；`糾正~；`扶正~。"},{"e":["例⃝「`匡救~」、「`匡助~」、「`匡時~`濟世~」。"],"f":"`輔助~；`幫助~；`救助~。"},{"e":["例⃝「`匡計~」、「`匡算~」、「`匡~`一~`匡~`這~`塊~`地面~`積~`有~`多~`大~」。"],"f":"〈`口~〉`約略~`計算~；`估計~。"},{"e":["例⃝「`日~`困~`而~`還~，`月~`盈~`而~`匡~`（~《`國語~‧`越~`語~`下~》）」。"],"f":"〈`書~〉`減損~。"},{"f":"`姓~。"}],"_":"1004190000","p":"kuāng","b":"ㄎㄨㄤ"}],"translation":{"francais":["corriger","redresser","aider","assister"],"Deutsch":["korrekt, abändern ","Kuang  (Eig, Fam)"],"English":["surname Kuang","to rectify"]}}