{"h":[{"d":[{"e":["例⃝「`要~`精通~`學問~`或~`技藝~`沒有~`捷徑~，`只要功夫深，鐵杵磨成針~」。"],"f":"〈`諺~〉`只要~`花費~`的~`時間~、`心力~`夠~`多~，`就~`連~`鐵~`杵~`也~`能~`磨~`成~`細~`針~。`比喻~`只要~`肯~`下~`苦功~`並~`持之以恆~，`再~`難~`的~`事情~`也~`能~`辦~`成~。"}],"A":"`只要~`功夫~`深~，铁`杵~`磨~`成~针","_":"1004930014","p":"zhǐyào gōngfū shēn,tiěchǔ móchéng zhēn<br>陸⃝zhǐyào gōngfu shēn,tiěchǔ móchéng zhēn","b":"ㄓˇ　ㄧㄠˋ　ㄍㄨㄥ　ㄈㄨ　ㄕㄣ，ㄊㄧㄝˇ　ㄔㄨˇ　ㄇㄛˊ　ㄔㄥˊ　ㄓㄣ<br>陸⃝ㄓˇ　ㄧㄠˋ　ㄍㄨㄥ　˙ㄈㄨ　ㄕㄣ，ㄊㄧㄝˇ　ㄔㄨˇ　ㄇㄛˊ　ㄔㄥˊ　ㄓㄣ"}],"translation":{"English":["If you work at it hard enough, you can grind an iron bar into a needle.","cf idiom `磨杵成針~|`磨~`杵~`成~针, to grind an iron bar down to a fine needle (idiom); fig. to persevere in a difficult task","to study diligently"]},"t":"`只要~`功夫~`深~，`鐵杵磨成針~"}