{"n":2,"t":"叫","r":"`口~","c":5,"h":[{"d":[{"e":["例⃝「`尖叫~」、「`喊叫~」、「`驚叫~」、「`大~`呼~`小~`叫~」。"],"f":"`喊~。"},{"e":["例⃝「`鳥~`叫~」、「`鳴叫~」、「`貓~`叫~」、「`警報器~`叫~`個~`不~`停~」。"],"f":"`動物~`或~`器物~`發出~`聲音~。"},{"e":["例⃝「`叫~`車~」、「`經理~`叫~`你~」。"],"f":"`呼喚~；`召喚~。"},{"e":["例⃝「`划拳~`也~`叫~`猜拳~」、「`這~`道~`小吃~`叫~`蚵仔煎~」。"],"f":"`稱~`為~；`稱~`做~。"},{"e":["例⃝「`真~`叫~`人~`討厭~」、「`叫~`孩子~`們~`聽話~」、「`醫生~`叫~`你~`要好~`好~`休息~」。"],"f":"`讓~；`命令~。"},{"e":["例⃝「`墨水~`瓶~`叫~`小弟~`弟~`打~`翻~`了~」、「`叫~`人~`批評~`得~`體無完膚~」。"],"f":"`介詞~。`引進~`動作~`行為~`的~`施~`事~`者~，`相當於~「`被~」、「`受~」`（~`多~`用~`於~`被動~`句~）。"},{"e":["例⃝「`叫~`驢~」。"],"f":"〈`口~〉`雄性~`的~。"}],"_":"1004910000","p":"jiào","b":"ㄐㄧㄠˋ"}],"translation":{"Deutsch":["heißen  (V)","rufen  (V)"],"English":["to shout","to call","to order","to ask","to be called","by (indicates agent in the passive mood)"]}}