{"n":7,"t":"唉","r":"`口~","c":10,"h":[{"d":[{"f":"`嘆詞~："},{"e":["例⃝「`唉~，`想不到~`事情~`會~`變成~`這樣~」。"],"f":"`表示~`嘆息~。"},{"e":["例⃝「`唉~，`我~`這~`就~`過去~」。"],"f":"`表示~`答應~。"}],"_":"1005950000","p":"āi","b":"ㄞ"},{"d":[{"e":["例⃝「`唉~，`全都~`搞砸~`了~」。"],"f":"`嘆詞~。`表示~`失望~、`惋惜~。`也~`作~「`噯~」。"}],"_":"1005950000","p":"āi<br>陸⃝ài","b":"ㄞ<br>陸⃝ㄞˋ"}],"translation":{"francais":["soupirer","(interjection d'accord)","hélas","couic","oh là là"],"Deutsch":["ach, oh, oh weh, oje <seufzend&gt  (Int)","ja <zustimmend "," bestätigend&gt  (Int)"],"English":["interjection or grunt of agreement or recognition (e.g. yes, it's me!)","to sigh","alas","oh dear"]}}