{"t":"`喇~`叭~","h":[{"d":[{"f":"`吹奏樂器~`名~。`多~`為~`銅~`製~，`前端~`小~，`身~`細長~`而~`漸~`大~，`尾端~`圓~`敞~。`軍~`中~`多~`用來~`傳達~`命令~。"},{"e":["例⃝「`汽車~`喇叭~」、「`音響~`喇叭~」。"],"f":"`揚聲器~`的~`通稱~。`把~`音頻~`信號~`轉換~`為~`聲波~`發送~`出去~`的~`器件~。`通常~`由~`磁鐵~、`線圈~`和~`紙~`盒~`構~`成~。`一般~`裝~`在~`擴音機~、`收音機~、`電視機~`上~。"},{"e":["例⃝「`這個~`大喇叭~`又~`在~`到處~`傳播~`他人~`是非~」。"],"f":"臺⃝`指~`話~`多~`的~`人~；`喜歡~`四處~`說~`人~`是非~`的~`人~。"}],"_":"1006310001","p":"lǎbɑ","b":"ㄌㄚˇ　˙ㄅㄚ"}],"translation":{"francais":["trompette","haut-parleur","klaxon"],"Deutsch":[" Lautsprecher, Megafon, \"Flüstertüte\", Hupe  (S)"],"English":["horn (automobile etc)","loudspeaker","brass wind instrument","trumpet","suona `鎖~`吶~|锁呐[suo3 na4]"]}}