{"h":[{"d":[{"f":"1894`年~6`月~23`日~，`由~`法~`國~`歷史~`學~`家~`古~`柏~`坦~`男爵~`（~Baron Pierrede Coubertin）`於~`巴~`黎~`會議~`創立~。`目的~`為~`發揚~`古~`希~`臘~`奧林匹克運動會~`的~`精神~，`增進~`世界~`友誼~，`促進~`人類~`和平~。`主要~`任務~`為~`管理~`並~`促進~`奧林匹克運動會~`的~`發展~，`具有~`法律~`地位~`及~`永久~`繼承權~。臺⃝`簡稱~「`國際奧會~」。陸⃝`簡稱~「`國際奧委會~」。"}],"A":"国际奥`林~`匹~`克~`委~员会","_":"1007340253","p":"guójì àolínpīkè wěiyuánhuì<br>陸⃝guójì àolínpǐkè wěiyuánhuì","b":"ㄍㄨㄛˊ　ㄐㄧˋ　ㄠˋ　ㄌㄧㄣˊ　ㄆㄧ　ㄎㄜˋ　ㄨㄟˇ　ㄩㄢˊ　ㄏㄨㄟˋ<br>陸⃝ㄍㄨㄛˊ　ㄐㄧˋ　ㄠˋ　ㄌㄧㄣˊ　ㄆㄧˇ　ㄎㄜˋ　ㄨㄟˇ　ㄩㄢˊ　ㄏㄨㄟˋ"}],"translation":{"Deutsch":["Internationales Olympisches Komitee  (S, Sport)"],"English":["International Olympic Committee"]},"t":"`國際~`奧~`林~`匹~`克~`委員會~"}