{"h":[{"d":[{"e":["例⃝「`凡~`侍~`於~`君~，`紳~`垂~，`足~`如~`履~`齊~，`頤~霤，`垂拱~，`視~`下~`而~`聽~`上~`（~《`禮記~‧`玉~`藻~》）」。"],"f":"〈`書~〉`雙手~`重疊~`在~`一起~`而~`垂下~，`以~`表示~`恭敬~。"},{"e":["例⃝「`惇~`信~`明~`義~，`崇~`德~`報~`功~，`垂拱~`而~`天下~`治~`（~《`書~`經~‧`武~`成~》）」。"],"f":"〈`書~〉`垂~`衣~`拱手~。`表示~`無為而治~。"},{"e":["例⃝「`農夫~`垂拱~`而~`無聊~`兮~，`釋~`其~`鉏~`耨~`而~`下~`淚~`（~`漢~‧`賈~`誼~〈`旱~`雲~`賦~〉）」。"],"f":"〈`書~〉`形容~`無~`事~`可~`做~。"},{"e":["例⃝「`吾~`欲~`移~`兵~`嶺~`北~，`廣~`收~`資~`實~，`須~`秦~`弊~`燕~`迴~，`然後~`垂拱~`取~`之~`（~《`晉~`書~‧`卷~`一一~`六~‧`姚~`萇~`載~`記~》）」。"],"f":"〈`書~〉`形容~`不~`費力~`氣~。"}],"_":"1007640027","p":"chuígǒng","b":"ㄔㄨㄟˊ　ㄍㄨㄥˇ"}],"t":"`垂~`拱~"}