{"n":9,"t":"場","r":"`土~","c":12,"h":[{"d":[{"e":["例⃝「`操場~」、「`會場~」、「`劇場~」。"],"f":"`空間~`較~`大~`的~`平坦~`地方~`或~`建築~。"},{"e":["例⃝「`上場~`比賽~」。"],"f":"`舞臺~`或~`活動~`場地~。"},{"e":["例⃝「`官場~」、「`逢場作戲~」。"],"f":"`指~`某~`種~`活動~`範圍~。"},{"e":["例⃝「`現場~」、「`當場~」。"],"f":"`事情~`發生~`的~`地點~。"},{"e":["例⃝「`開場~」、「`終場~」。"],"f":"`比賽~`或~`表演~`的~`整個~`過程~。"},{"e":["例⃝「`磁場~」、「`電場~」。"],"f":"`物質~`存在~`的~`一~`種~`基本~`形式~。"},{"f":"`量詞~："},{"e":["例⃝「`一~`場~`球賽~」、「`一~`場~`電影~」。"],"f":"(1)`用~`於~`計算~`娛樂~、`體育~`活動~。"},{"e":["例⃝「`第~`二~`幕~`第一~`場~」。"],"f":"(2)`用~`於~`計算~`戲劇~`中的~`小~`段落~。"},{"f":"`姓~。"}],"A":"场","_":"1007880000","p":"chǎng","b":"ㄔㄤˇ"},{"d":[{"e":["例⃝「`場院~」、「`場~`上~`堆~`滿~`了~`稻穀~」。"],"f":"`平坦~`的~`空地~。`多~`用來~`晒~`糧~`碾~`穀~。"},{"e":["例⃝「`趕場~」。"],"f":"陸⃝〈`口~〉`市~`集~。"},{"e":["例⃝「`一~`場~`大雨~」、「`朋友~`一~`場~」。"],"f":"`量詞~。`用~`於~`計算~`事情~`經過~。"}],"A":"场","_":"1007880000","p":"chǎng<br>陸⃝cháng","b":"ㄔㄤˇ<br>陸⃝ㄔㄤˊ"}],"translation":{"francais":["(dial.) digue en terre au bord d'une rivière ou d'une rizière (dans un but d'irrigation)"],"Deutsch":["Ort, Platz (S)","ZEW für Ereignisse, öffentliche Veranstaltungen, Spiele (Zähl)","Damm (Bestandteil von Ortsnamen mit dem Bezug auf einen Damm)  (Eig, Geo)"],"English":["threshing floor","classifier for events and happenings: spell, episode, bout","large place used for a specific purpose","stage","scene (of a play)","classifier for sporting or recreational activities","classifier for number of exams"]}}