{"t":"`天~`旋~`地~`轉~","h":[{"d":[{"e":["例⃝「`他~`不慎~`撞~`到~`牆壁~，`突然~`感~`到~`一陣~`天旋地轉~」、「`當年~`德~`軍~`攻陷~`巴~`黎~，`法人~`渾如~`天旋地轉~，`不知所措~」。"],"f":"`形容~`頭暈目眩~，`或~`比喻~`重大~`的~`變化~。"}],"A":"`天~`旋~`地~转","_":"1008490239","p":"tiānxuán-dìzhuǎn<br>陸⃝tiānxuán-dìzhuàn","b":"ㄊㄧㄢ　ㄒㄩㄢˊ　ㄉㄧˋ　ㄓㄨㄢˇ<br>陸⃝ㄊㄧㄢ　ㄒㄩㄢˊ　ㄉㄧˋ　ㄓㄨㄢˋ"}],"translation":{"francais":["Descent (jeu vidéo)"],"Deutsch":["Himmel und Erde scheinen sich vor jemanden zu drehen  (V)"],"English":["the sky spins, the earth goes round (idiom); giddy with one's head spinning","fig. huge changes in the world"]}}