{"n":11,"t":"寨","r":"`宀~","c":14,"h":[{"d":[{"e":["例⃝「`城~`寨~」。"],"f":"`古代~`防守~`用~`的~`柵欄~。"},{"e":["例⃝「`營寨~」、「`紮~`寨~」、「`拔~`寨~」。"],"f":"`古代~`的~`營房~。"},{"e":["例⃝「`寨~`主~」、「`山寨~」、「`壓寨夫人~」。"],"f":"`舊時~`指~`盜~`寇~`聚集~`的~`地方~。"},{"e":["例⃝「`寨子~」。"],"f":"`四周~`有~`柵欄~`或~`圍牆~`的~`村子~。"},{"f":"陸⃝`姓~。"}],"_":"1010470000","p":"zhài","b":"ㄓㄞˋ"}],"translation":{"Deutsch":["befestige Räuberhölle in den Bergen  (S)","befestigtes Dorf, von Palisaden umzäuntes Dorf  (S)","Befestigung der Banditen, Feste der Räuber  (S)","Feldlager, Heereslager  (S, Mil)","Lattenzaun, Palisade, Zaun  (S)"],"English":["stronghold","stockade","camp","(stockaded) village"]}}