{"t":"`張~`羅~","h":[{"d":[{"e":["例⃝「`張羅~`婚事~」、「`張羅~`一筆~`錢~」、「`他~`一個~`人~`張羅~`不過~`來~」。"],"f":"`籌劃~；`籌措~；`料理~。"}],"A":"张罗","_":"1012570148","p":"zhāngluó<br>陸⃝zhāngluo","b":"ㄓㄤ　ㄌㄨㄛˊ<br>陸⃝ㄓㄤ　˙ㄌㄨㄛ"}],"translation":{"francais":["assister à","s'activer à propos de","lever des fonds","saluer les invités"],"Deutsch":["beosrgen, verrichten, beschaffen , bewirten  (V)","verrichten, beschaffen, bedienen  (V)","bedienen  (V)"],"English":["to take care of","to raise money","to attend to (guests, customers etc)"]}}