{"t":"`想~`不~`到~","h":[{"d":[{"e":["例⃝「`想不到~`竟~`會~`在~`此~`遇見~`你~」、「`想不到~`一~`句~`無心~`的話~，`竟然~`惹~`出~`是非~」、「`想不到~`他~`竟~`在~`海外~`闖~`出~`一番~`名堂~`來~」、「`他~`年紀~`輕~`輕~`就~`患~`了~`癌症~，`真~`想不到~」。"],"f":"`沒有~`想~`到~；`出乎意料~。"}],"_":"1014030004","p":"xiǎngbúdào<br>陸⃝xiǎngbudào","b":"ㄒㄧㄤˇ　ㄅㄨˊ　ㄉㄠˋ<br>陸⃝ㄒㄧㄤˇ　˙ㄅㄨ　ㄉㄠˋ"}],"translation":{"francais":["inattendu","difficile à imaginer","inimaginable","il ne me serait pas venu à l'esprit que","qui aurait pu penser que... ?"],"Deutsch":["mit etw. nicht rechnen ","unerwartet ","unvorhergesehen "],"English":["unexpected","hard to imagine","it had not occurred to me","who could have thought that"]}}