{"t":"`愛~`面子~","h":[{"d":[{"e":["例⃝「`他~`這~`人~`愛面子~，`說話~`記得~`留~`些~`情面~」、「`明明~`就~`知道~`他~`愛面子~，`你~`還~`故意~`數落~`他~」。"],"f":"`看重~`自己~`的~`形象~，`生怕~`被~`人~`瞧不起~。"}],"A":"爱`面子~","_":"1014040025","p":"àimiànzi","b":"ㄞˋ　ㄇㄧㄢˋ　˙ㄗ"}],"translation":{"francais":["se préoccuper beaucoup des apparences","chercher à ne pas perdre la face","se préoccuper beaucoup de ses apparences","faire attention à sa réputation"],"Deutsch":["auf sein Ansehen bedacht sein "],"English":["to save face","to worry about losing face","proud of one's reputation","sensitive about losing prestige","sense of propriety"]}}