{"h":[{"d":[{"e":["例⃝「`抓緊~`車廂~`內~`的~`抓手~，`才~`不會~`跌倒~」。"],"f":"`用~`手~`抓~`握~`以~`保持~`身體~`平穩~`的~`東西~。"},{"e":["例⃝「`旅行~`箱~`抓手~」、「`起重機~`抓手~」。"],"f":"`可以~`用~`手~`握~`拿~`或~`操控~`的~`物件~`部位~。"},{"e":["例⃝「`以~`禮貌~`運動~`為~`抓手~，`全面~`提升~`服務~`水平~」、「`警~`民~`合作~`是~`打擊~`犯罪~`的~`有力~`抓手~」。"],"f":"`比喻~`進行~`某~`項~`工作~`的~`入手~`處~`或~`著力~`點~。"},{"f":"`某~`些~`地區~`指~`拉手~。"}],"S":"陸⃟","_":"1015210005","p":"zhuāshǒu","b":"ㄓㄨㄚ　ㄕㄡˇ"}],"translation":{"francais":["point de départ","main mécanique","pince"],"English":["starting point","mechanical hand","gripper"]},"t":"`抓~`手~"}