{"h":[{"d":[{"e":["例⃝「`這~`家~`公司~`以~`合法~`掩飾~`非法~，`真是~`掛羊頭賣狗肉~」。"],"f":"`掛~`的~`是~`羊~`頭~`而~`賣~`的~`是~`狗~`肉~。「`羊~`頭~」`比喻~「`好~`招牌~」，「`狗~`肉~」`比喻~「`壞~`品質~」，`指~`表裡不一~，`名不副實~。"}],"A":"`挂~`羊~头卖`狗~`肉~","_":"1016000012","p":"guà yángtóu mài gǒuròu","b":"ㄍㄨㄚˋ　ㄧㄤˊ　ㄊㄡˊ　ㄇㄞˋ　ㄍㄡˇ　ㄖㄡˋ"}],"translation":{"francais":["(expr. idiom.) accrocher une tête de mouton pour vendre de la viande de chien","tricher","publicité mensongère","mauvaises actions menées sous la bannière de la vertu"],"English":["lit. to hang a sheep's head while selling dog meat (idiom)","fig. to cheat","dishonest advertising","wicked deeds carried out under banner of virtue"]},"t":"`掛~`羊~`頭~`賣~`狗~`肉~"}