{"n":10,"t":"搭","r":"`手~","c":13,"h":[{"d":[{"e":["例⃝「`搭橋~」、「`搭~`帳篷~」。"],"f":"`架~`起~。"},{"e":["例⃝「`搭話~」、「`搭~`上線~」。"],"f":"`連結~；`連接~。"},{"e":["例⃝「`搭配~」、「`搭檔~」。"],"f":"`配合~。"},{"e":["例⃝「`搭~`船~」、「`搭~`飛機~」、「`搭便車~」。"],"f":"`乘坐~。"},{"e":["例⃝「`搭伙~」。"],"f":"`參加~；`加入~。"},{"e":["例⃝「`把手~`搭~`在~`別人~`的~`肩~`上~」、「`把~`毛巾~`搭~`在~`竹竿~`上~」。"],"f":"`把手~`或~`衣物~`等~`放~`在~`支撐~`物~`上~。"},{"e":["例⃝「`把~`這~`兩~`個人~`搭~`上~`應該~`夠~`了~」。"],"f":"`另外~`加上~。"},{"f":"`姓~。"}],"_":"1016390000","p":"dā","b":"ㄉㄚ"}],"translation":{"francais":["dresser","ériger","pendre","suspendre","joindre","se toucher","soulever","prendre (un transport)"],"English":["to put up","to build (scaffolding)","to hang (clothes on a pole)","to connect","to join","to arrange in pairs","to match","to add","to throw in (resources)","to take (boat, train)"]}}