{"n":5,"t":"政","r":"`攴~","c":9,"h":[{"d":[{"e":["例⃝「`參政~」、「`執政~」、「`政通人和~」。"],"f":"`政治~；`治理~`國家~`的~`事務~。"},{"e":["例⃝「`政壇~」、「`政令~」、「`政見~」。"],"f":"`政治~`的~。"},{"e":["例⃝「`警政~」、「`家政~」。"],"f":"`某~`一層~`面~`的~`事務~。"},{"e":["例⃝「`乞~`政~」、「`斧政~」。"],"f":"〈`書~〉`文字~`上~`的~`修改~`（~`多~`用~`於~`求救~`的~`敬辭~）。`通~「`正~」。"},{"f":"`姓~。"}],"_":"1017200000","p":"zhèng","b":"ㄓㄥˋ"}],"translation":{"francais":["politique","principes","gouvernement","administration"],"Deutsch":["best. staatl. Verwaltungsangelegenheit  (S)","Politik, politische Angelegenheit  (S)","politisch  (Adj)","Zheng  (Eig, Fam)","Angelegenheit einer Familie, Gemeinschaft [ hist. ] "],"English":["political","politics","government"]}}