{"t":"`敷~`衍~","h":[{"d":[{"e":["例⃝「`敷衍了事~」、「`敷衍~`搪塞~」、「`敷衍塞責~」。"],"f":"`做事~`搪塞~、`不負~`責任~，`僅~`表面~`應付~。"},{"e":["例⃝「`剩下~`的~`乾糧~`僅~`能~`敷衍~`一~`兩~`天~」、「`先~`敷衍~`敷衍~，`再~`想~`辦法~」。"],"f":"`勉強~`維持~；`（~`設法~）`應付~。"},{"e":["例⃝「`沖~`敷衍~`經~`旨~，`因~`以~`規~`諷~，`上~`未嘗~`不稱~`善~`（~《`宋~`史~‧`卷~`四~`三~`五~‧`儒~`林~`列傳~`五~‧`范~`沖~》）」。"],"f":"〈`書~〉`陳述~；`發揮~。"}],"_":"1017380002","p":"fūyǎn","b":"ㄈㄨ　ㄧㄢˇ"}],"translation":{"francais":["travailler pour la forme","bâcler","escamoter","faire le minimum"],"Deutsch":["oberflächlich, nachlässig handeln "],"English":["to elaborate (on a theme)","to expound (the classics)","perfunctory","to skimp","to botch","to do sth half-heartedly or just for show","barely enough to get by"]}}