{"n":5,"t":"某","r":"`木~","c":9,"h":[{"d":[{"e":["例⃝「`某~`人~」、「`某~`事~」、「`某~`年~」。"],"f":"`指~`代~`不特~`定~`的~`人~、`事~、`物~。"},{"e":["例⃝「`林~`某~」、「`某~`部~`官兵~」。"],"f":"`指~`特定~`或~`不宜~`說~`出名~`稱~`的~`人~`或~`單位~。"},{"e":["例⃝「`某~`雖~`不才~，`卻~`願意~`為國捐軀~」。"],"f":"`我~，`自稱~`之~`詞~。"},{"e":["例⃝「`林~`某~`老先生~」。"],"f":"`舊時~`凡~`應~`避諱~`之~`人名~`用~「`某~」`字~`代~。"},{"f":"臺⃝`姓~。"}],"_":"1018940000","p":"mǒu","b":"ㄇㄡˇ"},{"d":[{"f":"「`梅~」`的~`異體字~。"}],"_":"1018940000","p":"méi","b":"ㄇㄟˊ"}],"translation":{"francais":["certain","quelque","un tel","tel"],"Deutsch":["einige  (Zähl)","gewiss, bestimmt "],"English":["some","a certain","sb or sth indefinite","such-and-such"]}}