{"h":[{"d":[{"e":["例⃝「`禮單~`都~`上~`了~`檔子~`了~，`領~`謝~`名~`帖~`都~`交~`給~`各~`家~`的~`來人~`了~`（~《`紅~`樓~`夢~‧`第~`十~`一回~》）」。"],"f":"〈`書~〉`簿冊~；`卷宗~。"},{"f":"`量詞~："},{"e":["例⃝「`他~`都~`原諒~`你~`了~，`你~`就~`別~`再~`提~`那~`檔子~`事~`了~」。"],"f":"(1)`用~`於~`計算~`事情~，`相當於~「`件~」。"},{"e":["例⃝「`他~`知道~`父親~`愛~`熱鬧~，`便~`叫~`了~`一~`檔子~`雜耍~`來~`賀壽~」。"],"f":"(2)`用~`於~`計算~`成~`組~`的~`表演~`團體~。"}],"A":"档`子~","_":"1020330001","p":"dǎngzi<br>陸⃝dàngzi","b":"ㄉㄤˇ　˙ㄗ<br>陸⃝ㄉㄤˋ　˙ㄗ"}],"translation":{"English":["classifier for affairs, events etc"]},"t":"`檔~`子~"}