{"h":[{"d":[{"e":["例⃝「`我~`軍~`假設~`敵方~`轟炸機~`場~`的~`狀況~`做~`沙盤推演~」。"],"f":"`在~`沙盤~`上~`推估~`敵人~`的~`作戰~`方式~，`演練~`我~`方~`的~`因應~`之~`道~。"},{"e":["例⃝「`在~`上~`談判~`桌~`之前~，`董事長~`率領~`所有~`高階~`主管~`做~`沙盤推演~」。"],"f":"`在~`正式~`工作~`前~，`先~`對~`事情~`的~`可能~`發展~`做~`模擬~`評估~，`以便~`妥善~`因應~`所有~`變化~。"}],"A":"`沙~盘`推演~","_":"1021380074","p":"shāpán tuīyǎn","b":"ㄕㄚ　ㄆㄢˊ　ㄊㄨㄟ　ㄧㄢˇ"}],"translation":{"English":["to plan a military mission on a sand table (idiom)","to rehearse a planned action or activity","to conduct a dry run"]},"t":"`沙盤~`推演~"}