{"h":[{"p":"huóléifēng","S":"陸⃟","d":[{"e":["例⃝「`大家~`都~`稱讚~`他~`真是~`一~`位~`活雷鋒~」。"],"f":"`比喻~`像~`雷~`鋒~`一樣~`樂~`於~`奉獻~，`熱心~`助人~`的~`人~。`雷~`鋒~`（~1940－1962），`湖~`南~`望~`城~`人~，`中國~`解放軍~`軍人~、`中國~`共產黨~`黨員~。`立功~`多~`次~，`曾~`被~`評為~`節約~`標兵~，`並~`被~`選~`為~`撫~`順市~`人民~`代表~。`常~`利用~`假日~`作~`勞動~`服務~，`幫助~`人民~。1962`年~`因~`公~`殉職~，`毛~`澤~`東~`親~`題~「`向~`雷~`鋒~`同志~`學習~」。"}],"A":"`活~`雷~锋","_":"1021940089","b":"ㄏㄨㄛˊ　ㄌㄟˊ　ㄈㄥ"}],"translation":{"English":["selfless model citizen, just like Lei Feng `雷~`鋒~|`雷~锋[Lei2 Feng1]"]},"t":"`活~`雷~`鋒~"}