{"n":13,"t":"激","r":"`水~","c":16,"h":[{"d":[{"e":["例⃝「`溪~`水~`在~`岸邊~`激起~`朵~`朵~`浪花~」、「`一~`石~`激起~`千~`重~`浪~」。"],"f":"`水~`受~`到~`阻礙~`或~`震盪~`而~`湧~`起~`或~`濺~`起~。"},{"e":["例⃝「`激流~」、「`激情~」。"],"f":"`急劇~；`強烈~。"},{"e":["例⃝「`激昂~」、「`感激~」、「`激~`於~`義憤~」。"],"f":"`感情~`衝動~；`激動~。"},{"e":["例⃝「`激將法~」、「`激怒~」。"],"f":"`使~`激動~；`使~`發作~。"},{"e":["例⃝「`冷水~`一~`激~，`感冒~`了~」。"],"f":"`受~`冷水~`刺激~。"},{"e":["例⃝「`把~`啤酒~`瓶~`放~`在~`冰~`水~`裡~`激~`一~`激~」。"],"f":"陸⃝`放~`在~`冷水~`裡~`使~`降溫~。"},{"f":"`姓~。"}],"_":"1023500000","p":"jī","b":"ㄐㄧ"}],"translation":{"francais":["exciter","provoquer","vif","violent"],"English":["to arouse","to incite","to excite","to stimulate","sharp","fierce","violent"]}}