{"n":5,"t":"炸","r":"`火~","c":9,"h":[{"d":[{"e":["例⃝「`爆炸~」、「`熱水瓶~`炸~`了~」。"],"f":"`（~`物體~）`突然~`爆裂~。"},{"e":["例⃝「`轟炸~」、「`炸~`沉~`艦艇~」、「`橋~`梁~`被~`炸~`斷~`了~」。"],"f":"`用~`炸藥~、`炸彈~`摧毀~。"},{"e":["例⃝「`聽~`這~`話~`就~`氣~`炸~`了~」。"],"f":"〈`口~〉`怒氣~`突然~`發作~。"},{"e":["例⃝「`炸窩~」、「`炸~`群~」。"],"f":"陸⃝〈`口~〉`因~`受驚~`而~`逃散~。"}],"_":"1024000000","p":"zhà","b":"ㄓㄚˋ"},{"d":[{"e":["例⃝「`炸~`油條~」、「`炸~`肉丸~」。"],"f":"`烹調~`方法~，`把~`食物~`放~`在~`沸~`油~`裡~`使~`熟~。"},{"e":["例⃝「`把~`芹菜~`炸~`一下~」。"],"f":"陸⃝〈`口~〉`焯~，`把~`蔬菜~`放~`在~`開水~`裡~`略微~`一~`煮~`就~`撈~`出來~。"},{"e":["例⃝「`炸醬~」。"],"f":"`把~`某~`些~`食物~`和~`作料~`跟~`少量~`滾~`油~`混合~`烹~`炒~。"}],"_":"1024000000","p":"zhá","b":"ㄓㄚˊ"}],"translation":{"francais":["frire","faire frire","frit","éclater","copeaux"],"Deutsch":["frittieren, in Öl braten, ausbacken  (V)","explodieren "],"English":["to deep fry","to explode"]}}