{"n":5,"t":"為","r":"`火~","c":9,"h":[{"d":[{"e":["例⃝「`事在人為~」、「`膽大妄為~」。"],"f":"`做~。"},{"e":["例⃝「`為~`政~`清廉~」、「`種田~`為生~」、「`步步為營~」、「`為~`學~`之~`道~」。"],"f":"`表示~`某~`些~`行為~，`含~`有~`治理~、`從事~、`設置~、`研究~`等~`意義~。"},{"e":["例⃝「`有~`言~`為~`證~」、「`選~`他~`為~`代表~」。"],"f":"`當作~；`充當~。"},{"e":["例⃝「`化險為夷~」、「`一分為二~」。"],"f":"`變成~；`成為~。"},{"e":["例⃝「`識時務者為俊傑~」、「`失敗~`為~`成功~`之~`母~」。"],"f":"`是~。"},{"e":["例⃝「`大為~`肯定~」、「`極~`為~`優秀~」、「`頗為~`得意~」、「`廣~`為~`宣傳~」。"],"f":"`詞綴~。`附~`在~`某~`些~`單~`音節~`詞~`後面~，`構~`成~`表示~`程度~`或~`範圍~`的~`副詞~。"},{"e":["例⃝「`為~`風雨~`所~`阻~」、「`為~`民眾~`所~`贊成~」。"],"f":"`介詞~。`引進~`施~`事~`者~`（~`常~`與~「`所~」`搭配~`使用~）。"},{"f":"`姓~。"}],"A":"为","_":"1023950000","p":"wéi","b":"ㄨㄟˊ"},{"d":[{"e":["例⃝「`他~`是~`真心~`為~`你~」、「`為人~`就~`要~`為~`到底~」。"],"f":"`幫助~。"},{"f":"`介詞~："},{"e":["例⃝「`為~`民族~`爭光~」、「`為~`老百姓~`謀~`福祉~」。"],"f":"(1)`引進~`動作~`行為~`的~`受益~`者~，`相當於~「`替~」`或~「`給~」。"},{"e":["例⃝「`為~`他~`的~`成功~`而~`乾杯~」、「`為~`國家~`的~`富強~`而~`奮鬥~」。"],"f":"(2)`引進~`動作~`行為~`的~`原因~`或~`目的~，`相當於~「`由於~」`或~「`為了~」。"}],"A":"为","_":"1023950000","p":"wèi","b":"ㄨㄟˋ"}],"translation":{"Deutsch":["fungieren als, verhalten als, auftreten als  (V)","sein, betragen  (V)","wegen, um, im Bestreben  (Konj)"],"English":["as (in the capacity of)","to take sth as","to act as","to serve as","to behave as","to become","to be","to do","by (in the passive voice)","because of","for","to"]}}