{"h":[{"d":[{"f":"`生態系~`中的~`群落~`和~`其~`組成~`成分~`經由~`各種~`對立~`因素~，`透過~`相互~`制約~、`轉化~、`補償~、`反饋~、`交換~`等~`作用~，`使~`其~`結構~`與~`功能~`達到~`一個~`相對~`穩定~`的~`平衡~`狀態~。`包括~`生物~`種類~`的~`組成~、`各個~`種群~`的~`數量~`比例~`以及~`能量~`和~`物質~`的~`輸入~、`輸出~`等~`都~`處於~`相對~`穩定~`的~`狀態~，`這~`種~`狀態~`稱~`作~`生態平衡~。`也~`作~「`自然平衡~」。"}],"A":"`生~态`平衡~","_":"1026230258","p":"shēngtài pínghéng","b":"ㄕㄥ　ㄊㄞˋ　ㄆㄧㄥˊ　ㄏㄥˊ"}],"translation":{"francais":["équilibre de la nature","équilibre biologique","équilibre écologique"],"Deutsch":["ökologisches Gleichgewicht  (S)"]},"t":"`生態~`平衡~"}