{"t":"`用~`人~","h":[{"d":[{"e":["例⃝「`用人~`標準~」、「`用人~`不~`疑~」、「`用人~`的~`藝術~」。"],"f":"`任用~`人員~。"},{"e":["例⃝「`農忙~`之~`際~，`正是~`用人~`之~`時~」。"],"f":"`需要~`人手~。"}],"_":"1026270001","p":"yòngrén","b":"ㄩㄥˋ　ㄖㄣˊ"},{"d":[{"f":"`被~`僱用~`的~`人~；`幫~`佣~`的~`僕役~。`也~`作~「`佣~`人~」。"}],"_":"1026270001.001","p":"yòngrén<br>陸⃝yòngren","b":"ㄩㄥˋ　ㄖㄣˊ<br>陸⃝ㄩㄥˋ　˙ㄖㄣ"}],"translation":{"francais":["sélection professionnelle","choisir qqn pour lui confier un travail","utiliser les capacités des gens"],"Deutsch":["Diener, Dienstmädchen, Hausangestellte "],"English":["servant","to employ sb for a job","to manage people","to be in need of staff"]}}