{"h":[{"d":[{"e":["例⃝「`好漢~`不~`提~`當年~`勇~」、「`當年~`的~`學術~`骨幹~`現今~`都~`退~`下來~`了~」。"],"f":"`指~`從前~`的~`某~`一~`年~`或~`某~`個~`時候~。"},{"e":["例⃝「`他~`正當年~，`幹活兒~`渾身~`都~`是~`勁~」。"],"f":"`指~`年齡~`處在~`身強力壯~`的~`階段~。"}],"A":"当`年~","_":"1026520027","p":"dāngnián","b":"ㄉㄤ　ㄋㄧㄢˊ"},{"d":[{"e":["例⃝「`當年~`栽~`樹~`當年~`歇涼~」、「`當年~`的~`債務~`當年~`還清~」。"],"f":"`事情~`發生~`的~`同一~`年~；`本~`年~。"}],"A":"当`年~","_":"1026520027.001","p":"dàngnián","b":"ㄉㄤˋ　ㄋㄧㄢˊ"}],"translation":{"francais":["cette année-là","l'année même"],"English":["in those days","then","in those years","during that time"]},"t":"`當~`年~"}