{"n":11,"t":"瘻","r":"`疒~","c":16,"h":[{"d":[{"f":"〈`書~〉`頸部~`腫大~`症~，`多~`因~`缺~`碘~`引起~。"},{"f":"`瘻管~`的~`本名~。`因~`先天~`發育~`異常~、`外傷~、`炎症~、`感染~、`或~`手術~`併發症~`等~`引起~`的~`異常~`通道~，`例如~`管~`腔~`臟器~`與~`體表~`或~`兩~`個~`管~`腔~`臟器~`之~`間~`的~`非~`正常~`通道~。`病灶~`內~`的~`分泌~`物~`可~`經由~`瘻管~`流~`出~。`也~`作~「`瘺~」。"},{"f":"`中醫~`指~`深~`部~`組織~`或~`淋巴結~`因~`感染~`或~`發炎~，`造成~`膿~`或~`分泌~`物~`由~`管道~`向~`身體~`表面~`流~`出~`或~`體~`內~`兩~`個~`腔~`室~`相通~。"}],"A":"瘘","_":"4086030000","p":"lòu","b":"ㄌㄡˋ"}],"translation":{"francais":["ulcère purulent"],"English":["fistula","ulceration"]}}