{"h":[{"d":[{"e":["例⃝「`新~`穀~`登場~」。"],"f":"`（~`把~`收割~`的~`穀物~）`運~`到場~`上~。"}],"A":"`登~场","_":"1027190056","p":"dēngchǎng<br>陸⃝dēngcháng","b":"ㄉㄥ　ㄔㄤˇ<br>陸⃝ㄉㄥ　ㄔㄤˊ"},{"d":[{"e":["例⃝「`登場~`演出~」、「`粉墨登場~」、「`袍笏登場~」。"],"f":"`（~`劇中人~）`走~`上~`舞臺~。"}],"A":"`登~场","_":"1027190056.001","p":"dēngchǎng","b":"ㄉㄥ　ㄔㄤˇ"}],"translation":{"francais":["entrer en scène","parvenir sur l'aire de battage","arriver à maturité"],"English":["to go on stage","fig. to appear on the scene","used in advertising to mean new product"]},"t":"`登~`場~"}