{"t":"`百年~`樹人~","h":[{"d":[{"e":["例⃝「`百年樹人~，`國~`之~`大計~」。"],"f":"`形容~`培養~`人才~`的~`不容~`易~`（~`常~`與~「`十~`年~`樹~`木~」`連用~）。"}],"A":"`百年~树`人~","_":"1027220047","p":"bǎinián-shùrén","b":"ㄅㄞˇ　ㄋㄧㄢˊ　ㄕㄨˋ　ㄖㄣˊ"}],"translation":{"francais":["(expr. idiom.) Il faut dix ans pour nourrir un arbre, mais une centaine d'années pour former un homme"],"Deutsch":["zur Herausbildung fähige Menschen bedarf es vieler Jahre  (Sprichw)"],"English":["It takes ten years to nurture a tree, but a hundred years to train a man (idiom)","fig. a good education program takes a long time to develop","cf. `十年樹木，百年樹人~|`十~`年~树`木~，`百年~树`人~"]}}