{"n":0,"t":"皮","r":"`皮~","c":5,"h":[{"d":[{"e":["例⃝「`臉皮~」、「`貂皮~」、「`樹~`皮~」。"],"f":"`動~`植物~`的~`表層~`組織~。"},{"e":["例⃝「`皮鞋~」、「`皮襖~」、「`皮箱~」。"],"f":"`皮革~`製~`成~`的~。"},{"e":["例⃝「`皮~`糖~」、「`皮紙~」。"],"f":"`有~`韌性~`的~；`不~`酥~`脆~。"},{"e":["例⃝「`皮實~」。"],"f":"`不~`嬌嫩~；`結實~。"},{"e":["例⃝「`橡皮~」、「`膠皮~」。"],"f":"`指~`橡膠~。"},{"e":["例⃝「`皮球~」、「`皮蛋~」。"],"f":"`有~`彈性~`的~。"},{"e":["例⃝「`水~`皮~」、「`地皮~」。"],"f":"`泛指~`物體~`的~`表面~。"},{"e":["例⃝「`皮相~`（~ㄒ`丨~ㄤˋ　xiàng）」、「`浮皮潦草~」。"],"f":"`表面~`的~；`膚淺~`的~。"},{"e":["例⃝「`封皮~」、「`書皮~」、「`餃子~`皮~」。"],"f":"`包~`在外~`面~`的~`東西~。"},{"e":["例⃝「`鐵皮~」、「`粉皮~`兒~」、「`嘴皮子~」、「`豆腐皮~`兒~」。"],"f":"`某~`些~`薄片~`狀~`的~`東西~。"},{"e":["例⃝「`調皮~」、「`這~`孩子~`真皮~」。"],"f":"`頑皮~；`淘氣~。"},{"e":["例⃝「`他~`成天~`挨罵~，`早就~`皮~`了~」。"],"f":"`因~`多~`次~`受~`批評~`或~`責罵~，`而~`滿不在乎~。"},{"f":"`姓~。"},{"f":"`二~`一~`四部~`首~`之~`一~。"}],"_":"1027320000","p":"pí","b":"ㄆㄧˊ"}],"translation":{"francais":["peau","écorce","cuir","surface","enveloppe","espiègle","insensible"],"Deutsch":[" Hülle, dünner Teig ","Leder, Haut "],"English":["surname Pi","leather","skin","fur","CL:`張~|张[zhang1]","pico- (one trillionth)","naughty"]}}