{"t":"`目~`瞪~`口~`呆~","h":[{"d":[{"e":["例⃝「`眼前~`壯美~`的~`瀑布~`奇觀~，`讓~`他~`目瞪口呆~」、「`證人~`一~`出現~，`犯罪嫌疑人~`頓時~`嚇~`得~`目瞪口呆~」。"],"f":"`兩~`眼~`直~`瞪~`著~，`說~`不~`出~`話~`來~。`形容~`因~`詫異~`或~`害怕~`而~`發愣~`的~`樣~`子~。"}],"_":"1027560058","p":"mùdèng-kǒudāi","b":"ㄇㄨˋ　ㄉㄥˋ　ㄎㄡˇ　ㄉㄞ"}],"translation":{"francais":["rester bouche bée","être frappé de stupeur","être abasourdi","ahuri","stupéfait","ébahi"],"Deutsch":["betäubt  (Adj)","erstaunt  (Adj)","sprachlos  (Adj)","verblüfft  (Adj)","verwirrt  (Adj)"],"English":["dumbstruck (idiom); stupefied","stunned"]}}