{"t":"`統~`計~","h":[{"d":[{"e":["例⃝「`統計~`一下~`數字~」。"],"f":"`總括~`地~`計算~。"},{"e":["例⃝「`統計學~」、「`大量~`數據~`要~`統計~`處理~」。"],"f":"`蒐集~`某~`一~`現象~`的~`有關~`數據~，`並~`對~`其~`進行~`整理~、`分析~`和~`推斷~`等~，`即~`做~`統計~`工作~。"},{"e":["例⃝「`這個~`統計~`還~`須~`進一步~`核實~」。"],"f":"`指~`經~`統計~`所~`獲得~`的~`資料~。"},{"f":"`指~`統計學~。`即~`研究~`統計~`理論~`與~`方法~`的~`學科~。"}],"A":"统计","_":"1031040026","p":"tǒngjì","b":"ㄊㄨㄥˇ　ㄐㄧˋ"}],"translation":{"francais":["statistique","compter"],"Deutsch":["Statistik  (S)"],"English":["statistics","to count","to add up"]}}