{"t":"`老~`爺~","h":[{"d":[{"e":["例⃝「`知府~`老爺~」、「`做官~`當~`老爺~」、「`他~`的~`命~`好~`得~`很~，`在家~`當~`老爺~」。"],"f":"`舊時~`用~`於~`稱~`官吏~`或~`有~`權~`勢~`的~`人~；`現~`多~`用~`於~`諷刺~`高高在上~、`只~`圖~`享受~`的~`人~。"},{"f":"`舊時~`僕人~`對~`年長~`男~`主人~`的~`稱呼~。"},{"e":["例⃝「`老爺~`貨~」、「`老爺~`機床~」。"],"f":"`比喻~`陳舊~`過時~`的~。"},{"f":"陸⃝〈`口~〉`外祖父~。`也~`作~「`姥爺~」。"}],"A":"`老~爷","_":"1032510303","p":"lǎoyé<br>陸⃝lǎoye","b":"ㄌㄠˇ　ㄧㄝˊ<br>陸⃝ㄌㄠˇ　˙ㄧㄝ"}],"translation":{"francais":["grand-père (maternel)","seigneur"],"Deutsch":["Großvater mütterlicherseits  (S)"],"English":["(respectful) lord","master","(coll.) maternal grandfather"]}}