{"n":5,"t":"聃","r":"`耳~","c":11,"h":[{"d":[{"e":["例⃝「`聃~`耳~`屬~`（~ㄓㄨˇ　zhǔ，`連接~）`肩~，`綺~`眉~`覆~`顴~`（~`宋~‧`蘇~`軾~〈`補~`禪~`月~`羅漢~`贊~〉`九~`首~`之~`二~）」。"],"f":"〈`書~〉`耳~`大~`且~`長~。"},{"e":["例⃝「`方~`其~`聃~`于~`色~`也~，`屏~`親昵~，`絕交~`遊~`（~《`列~`子~‧`楊~`朱~》）」。"],"f":"〈`書~〉`沉迷~。`通~「`耽~」。"},{"f":"`用~`於~`人名~。`春秋~`時~`思想家~`李~`耳~`的~`字~，`老~`聃~，`即~`老子~`（~ㄗˇ　zǐ）。"}],"_":"2036070000","p":"dān","b":"ㄉㄢ"}],"translation":{"francais":["(prénom)"],"Deutsch":["Dan (Einer der Namen des Laozi: `老~`聃~ - Altes Langohr)  (Eig, Fam)"],"English":["ears without rim"]}}