{"t":"`聯~`結~","h":[{"d":[{"e":["例⃝「`民族~`情感~`把~`世界~`各~`地~`的~`華人~`聯結~`在~`一起~」。"],"f":"`聯繫~`結合~`（~`在~`一起~）。"},{"f":"`透過~`網路~`的~`傳遞~，`使~`兩~`地~`電腦~`設備~`能夠~`相互~`的~`溝通~`及~`傳遞~`訊息~；`或~`指~`兩~`部~`以上~`電腦~，`利用~`某~`種~`形式~`呈~`連線~`狀態~。∥`也~`作~「`連結~」`（~陸⃝`今~`不用~）。"}],"A":"联结","_":"1032770058","p":"liánjié","b":"ㄌㄧㄢˊ　ㄐㄧㄝˊ"}],"translation":{"francais":["liaison","coupler","couplage"],"Deutsch":["verbinden, binden ","Koppelung  (S)","Kupplung  (S)","Zusammenfügung  (S)","koppeln  (V)"],"English":["to bind","to tie","to link"]}}