{"n":19,"t":"虀","r":"`艸~","c":23,"h":[{"d":[{"e":["例⃝「`向來~`道~`邊~`有~`賣~`餅~`家~`蒜~`虀~`大~`酢~，`從~`取~`三~`升~`飲~`之~，`病~`自當~`去~`（~《`三國志~‧`卷~`二~`十~`九~‧`魏~`書~‧`方技~`傳~‧`華~`佗~》）」。"],"f":"〈`書~〉`薑~、`蒜~`等~`的~`碎~`末~，`供~`調味~`用~。"},{"e":["例⃝「`苗~`欲~`走~，`四面~`圍~`定~，`砍~`為~`虀~`粉~`（~《`三國~`演義~‧`第~`三~`回~》）」。"],"f":"〈`書~〉`細碎~。‖`同~「`齏~」。"},{"e":["例⃝「`若~`向~`其間~`尋~`穩便~，`一~`壺~`濁~`酒~`一~`餐~`虀~`（~《`警世~`通~`言~•`卷~`二~`十~`六~•`唐~`解元~`一~`笑~`姻緣~》）」。"],"f":"〈`書~〉`細~`切~`的~`鹹菜~、`醬菜~。"}],"_":"2041880000","p":"jī","b":"ㄐㄧ"}],"translation":{"francais":["fragment","légumes salés","épices"],"Deutsch":["Bruchstück, Fragment  (S)","Gewürze  (S)"],"English":["fragment","salted vegetables","spices"]}}