{"n":6,"t":"裁","r":"`衣~","c":12,"h":[{"d":[{"e":["例⃝「`裁~`衣~」、「`裁~`紙~」、「`裁~`布~」。"],"f":"`用~`刀~、`剪~`等~`把~`布~、`紙~`等~`片~`狀~`物~`分割~`開~。"},{"e":["例⃝「`裁員~」、「`裁軍~」、「`裁~`有餘~`而~`補~`不足~」。"],"f":"`削減~；`消除~`多餘~`的~`部分~。"},{"e":["例⃝「`制裁~」、「`獨裁~」。"],"f":"`控制~；`節制~。"},{"e":["例⃝「`仲裁~」、「`裁決~」、「`裁定~」。"],"f":"`經~`權衡~`而~`作~`出~`判斷~`或~`決定~。"},{"e":["例⃝「`獨出心裁~」。"],"f":"`（~`在~`文學~`藝術~`創作~`中~）`對~`題材~`等~`進行~`取捨~`安排~。"},{"e":["例⃝「`體裁~」。"],"f":"`指~`文章~`的~`體制~`或~`樣~`式~。"},{"e":["例⃝「`十~`六~`裁~`紙~`（~`一~`整~`張~`紙~`的~`十~`六~`分~`之~`一~）」。"],"f":"`量詞~。`用~`於~`計算~`整~`張~`紙~`分成~`的~`等分~。"}],"_":"1037230000","p":"cái","b":"ㄘㄞˊ"}],"translation":{"francais":["tailler","couper","réduire","diminuer","renvoyer","sanctionner"],"Deutsch":["herausgeschnitten (als Kleid), geschnitten, Ordnung, verringern, vermindern, Entscheidung, Urteil "],"English":["to cut out (as a dress)","to cut","to trim","to reduce","to diminish","to cut back (e.g. on staff)","decision","judgment"]}}