{"n":6,"t":"裂","r":"`衣~","c":12,"h":[{"d":[{"e":["例⃝「`破裂~」、「`裂開~」、「`分裂~」、「`四分五裂~」。"],"f":"`破~；`分散~。"},{"e":["例⃝「`裂縫~」、「`裂痕~」、「`裂紋~」。"],"f":"`出現~`縫隙~`（~`尚未~`分開~）。"}],"_":"1037240000","p":"liè","b":"ㄌㄧㄝˋ"},{"d":[{"e":["例⃝「`褲~`縫~`兒~`裂~`了~`個~`大口~`子~」、「陸⃝`裂~`著~`懷~`吹風~」。"],"f":"〈`口~〉`向~`兩邊~`分開~；`敞開~。"}],"_":"1037240000","p":"liè<br>陸⃝liě","b":"ㄌㄧㄝˋ<br>陸⃝ㄌㄧㄝˇ"}],"translation":{"francais":["se fendre","crever"],"Deutsch":["platzen. zersplittern; Spalte "],"English":["to split","to crack","to break open","to rend"]}}