{"t":"`要~`命~","h":[{"d":[{"e":["例⃝「`這~`是~`要命~`的~`病~」、「`即使~`要命~`也~`不能~`喪失~`氣節~」。"],"f":"`致命~；`使~`喪失~`生命~。"},{"e":["例⃝「`真~`要命~，`你~`怎麼~`現在~`才~`來~！」。"],"f":"`形容~`使~`人~`陷於~`困境~，`難以忍受~`（~`含~`埋怨~`意~）。"},{"e":["例⃝「`天~`冷~`得~`要命~」、「`難受~`得~`要命~」、「`這~`人~`懶得~`要命~」。"],"f":"`形容~`程度~`極~`高~。"}],"_":"1037630023","p":"yàomìng","b":"ㄧㄠˋ　ㄇㄧㄥˋ"}],"translation":{"francais":["qui rend la vie impossible","tuer","extrêmement","mortellement","terriblement"],"Deutsch":["als Kompl: auf die Nerven gehen, was für ein Pech ","Belästigung  (S)","furchtbar, äußerst  (Adj)"],"English":["to cause sb's death","very","extremely","frightening","annoying"]}}