{"h":[{"d":[{"f":"`書~`名~。`東漢~‧`許~`慎~`著~。`共~`三~`十~`卷~。`收錄~`小篆~`九~`三~`五~`三~`字~，`兼~`收~`古文~、`籀文~`等~`一一~`六~`三~`字~`為重~`文~。`創立~`部首~，`依~`文字~`形體~`及~`偏旁~`構造~`分列~`五~`百~`四~`十~`部~。`每~`字~`大抵~`先~`釋~`字義~，`再說~`明~`形體~`結構~`及~`音~`讀~。`是~`我~`國~`第一~`部~`有~`系統~`分析~`字形~、`字音~、`字義~`的~`書籍~。`晚近~`注~`家~`以~`清~‧`段~`玉~`裁~、`桂~`馥~、`朱~`駿~`聲~、`王~`筠~`最~`為~`精~`博~。`又~`名~《`說~`文~》。"}],"A":"说`文~`解~`字~","_":"1038390009","p":"shuōwén-jiězì","b":"ㄕㄨㄛ　ㄨㄣˊ　ㄐㄧㄝˇ　ㄗˋ"}],"translation":{"Deutsch":["Shuowen Jiezi (\"Erklärung der einfachen Zeichen und Erläuterung der zusammengesetzten Zeichen\", ältestes Zeichenlexikon der chinesischen Sprache) (Eig, Werk, Autor: Xu Shen)"],"English":["Shuowen Jiezi, the original Han dynasty Chinese character dictionary with 10,516 entries, authored by Xu Shen `許~`慎~|许`慎~[Xu3 Shen4] in 2nd century"]},"t":"`說~`文~`解~`字~"}