{"n":4,"t":"貨","r":"`貝~","c":11,"h":[{"d":[{"e":["例⃝「`進貨~」、「`奇貨可居~」。"],"f":"`貨物~；`商品~。"},{"e":["例⃝「`蠢貨~」、「`賤貨~」、「`笨貨~」。"],"f":"`稱~`有~`某~`種~`不良~`品行~`或~`無能~`的~`人~`（~`用~`於~`罵人~`或~`取笑~`人~）。"},{"e":["例⃝「`貨幣~」、「`通貨~」。"],"f":"`錢幣~。"},{"e":["例⃝「`殺人越貨~」、「`八~`政~：`一~`曰~`食~，`二~`曰~`貨~`（~《`書~`經~‧`洪~`範~》）」。"],"f":"〈`書~〉`錢財~、`珠寶~、`布帛~`等~`的~`統稱~。"},{"f":"陸⃝`姓~。"}],"A":"货","_":"1039350000","p":"huò","b":"ㄏㄨㄛˋ"}],"translation":{"francais":["marchandise"],"Deutsch":["Geld _s_  (S)","Ware  (S)"],"English":["goods","money","commodity","CL:`個~|个[ge4]"]}}