{"h":[{"d":[{"e":["例⃝「`超升~`天~`界~`當~`神~，`人間~`立~`廟~`奉祀~」。"],"f":"`道教~`用語~。`指~`得道~`成~`仙~，`上升~`天~`界~。"},{"e":["例⃝「`作惡多端~，`小心~`死~`後~`打~`入~`地獄~，`不得~`超升~」。"],"f":"`佛教~`用語~。`指~`人~`死~`後~`經~`佛法~`超度~，`靈魂~`可~`往生~`極樂世界~。"},{"e":["例⃝「`無~`一技之長~，`又~`好吃懶做~，`貧窮~`困境~，`何~`能~`超升~？」。"],"f":"`比喻~`從~`困境~`中~`解脫~。"},{"e":["例⃝「`課~`績~`高~`者~，`不~`次~`超升~`（~《`舊~`唐~`書~‧`卷~`一~`三八~‧`趙~`憬~`列傳~》）」。"],"f":"〈`書~〉`越~`等~`升級~。"}],"_":"1039940016","p":"chāoshēng","b":"ㄔㄠ　ㄕㄥ"}],"translation":{"Deutsch":["Erhebung, Erhöhung  (S)"],"English":["exaltation"]},"t":"`超~`升~"}