{"t":"`迫~`降~","h":[{"d":[{"e":["例⃝「`切斷~`敵人~`退路~，`圍困~`迫降~」。"],"f":"`迫使~`投降~。"}],"_":"1041260013","p":"pòxiáng","b":"ㄆㄛˋ　ㄒㄧㄤˊ"},{"d":[{"e":["例⃝「`發動機~`漏~`油~`導致~`客機~`迫降~」。"],"f":"`（~`飛機~）`因~`某~`種~`原因~`被迫~`降落~。"},{"e":["例⃝「`迫降~`敵機~`兩~`架~」。"],"f":"`強迫~`飛機~`在~`指定~`機場~`降落~。"}],"_":"1041260013.001","p":"pòjiàng","b":"ㄆㄛˋ　ㄐㄧㄤˋ"}],"translation":{"francais":["contrainte d'atterrissage","contraindre à atterrir"],"Deutsch":["Notlandung  (S)"],"English":["to force a plane to land","to force sb to surrender"]}}