{"t":"`過~`渡~","h":[{"d":[{"e":["例⃝「`大~`橋~`尚未~`建~`成~，`人們~`只有~`乘~`船~`才能~`過渡~`到~`對岸~」。"],"f":"`通過~`江河~。"},{"e":["例⃝「`過渡時期~」、「`語調~`由~`輕~`緩~、`低沉~`逐步~`過渡~`到~`急促~、`高亢~」。"],"f":"`（~`事物~）`從~`一個~`階段~`或~`一~`種~`狀態~`逐步~`發展~`轉變~`到~`另~`一個~`階段~`或~`另~`一~`種~`狀態~。"}],"A":"过`渡~","_":"1041670103","p":"guòdù","b":"ㄍㄨㄛˋ　ㄉㄨˋ"}],"translation":{"francais":["transiter","passer de ... à ...","excessif"],"Deutsch":["interim  (Adj)","vorübergehend, zwischenzeitlich  (Adj)"],"English":["to cross over (by ferry)","transition","interim","caretaker (administration)"]}}