{"t":"`非~`常~","h":[{"d":[{"e":["例⃝「`元宵~`燈會~，`熱鬧~`非常~」、「`非常時期~」、「`非常~`之~`功~」。"],"f":"`異乎尋常~`的~；`特殊~`的~。"},{"e":["例⃝「`非常~`努力~」、「`非常~`虔誠~」、「`非常~`非常~`有道~`理~」、「`非常~`非常~`想念~`媽媽~」。"],"f":"`表示~`程度~`極~`高~，`相當於~「`十分~」、「`極其~」。"}],"_":"1045030047","p":"fēicháng","b":"ㄈㄟ　ㄔㄤˊ"}],"translation":{"francais":["extraordinaire","exceptionnel","très","extrêmement"],"Deutsch":["ungewöhnlich, außerordentlich, übermäßig, sehr, außergewöhnlich  (Adj)"],"English":["unusual","extraordinary","extreme","very","exceptional"]}}