{"n":4,"t":"頓","r":"`頁~","c":13,"h":[{"d":[{"e":["例⃝「`橫~`的~`起筆~`和~`收~`筆~`都~`要~`頓~`一頓~」。"],"f":"`書寫~`時~，`使~`筆~`用力~`著~`（~ㄓㄨㄛˊ　zhuó）`紙~`稍~`作~`停留~。"},{"e":["例⃝「`捶胸頓足~」、「`用~`手杖~`頓~`著地~」。"],"f":"`用~`腳~`跺~`地~；`用~`器物~`連續~`地~`觸~`地~。"},{"e":["例⃝「`困頓~」、「`勞頓~」、「`委頓~」。"],"f":"`疲勞~；`困倦~。"},{"e":["例⃝「`安頓~」、「`整頓~」。"],"f":"`安置~；`安排~。"},{"e":["例⃝「`停頓~」、「`頓號~」、「`抑揚頓挫~」、「`說~`著~`說~`著~，`忽然~`頓~`了~`一下~」。"],"f":"`停~`下來~；`稍~`停~。"},{"e":["例⃝「`頓悟~」、「`頓覺~`前非~」、「`茅塞頓開~」。"],"f":"`表示~`時間~`短促~，`相當於~「`立刻~」、「`忽然~」。"},{"e":["例⃝「`頓首~」。"],"f":"〈`書~〉`用~`頭~`叩~`地~。"},{"e":["例⃝「`逐~`水草~`而~`頓~」、「`頓~`師~`城~`下~」。"],"f":"〈`書~〉`停~`下來~`住宿~；`屯~`駐~。"},{"f":"`量詞~："},{"e":["例⃝「`一天~`三~`頓~`飯~」、「`頓~`頓~`吃~`得~`好~」。"],"f":"(1)`用~`於~`計算~`飯食~`的~`次數~。"},{"e":["例⃝「`罵~`了~`一頓~」、「`一頓~`教訓~」、「`被~`打~`了~`一頓~」。"],"f":"(2)`用~`於~`計算~`斥責~、`勸說~、`打罵~`等~`行為~`的~`次數~。"},{"f":"`姓~。"}],"A":"顿","_":"1045440000","p":"dùn","b":"ㄉㄨㄣˋ"},{"d":[{"f":"`參見~【`冒頓~】。"}],"A":"顿","_":"1045440000","p":"dú","b":"ㄉㄨˊ"}],"translation":{"francais":["faire une pause","frapper du pied","soudain","imédiatement","(classificateur pour les repas et les réprimandes)"],"Deutsch":["ZEW für einmalige Handlungen ohne Wiederholung (Zähl)"],"English":["to stop","to pause","to arrange","to lay out","to kowtow","to stamp (one's foot)","at once","classifier for meals, beatings, scoldings etc: time, bout, spell, meal"]}}