{"n":10,"t":"鰤","r":"`魚~","c":21,"h":[{"d":[{"f":"`魚~`名~。`體~`呈~`紡錘~`形~，`鱗~`小~`而~`圓~，`尾鰭~`分~`叉~。`背~`藍~`灰色~，`腹~`白色~；`有~`些~`種~`幼~`魚~`時~`體~`側~`具~`橫~`帶~，`成~`魚~`則~`消失~。`棲息~`於~`岸邊~`至~`大陸棚~`緣~`水~`深~20-150`公尺~`處~。`獨~`游~。`以~`小型~`魚~`及~`無脊椎動物~`為~`食~。`廣泛~`分布~`於~`印度洋~、`太平洋~`等~`熱帶~`及~`亞熱帶~`海域~。`是~`常見~`之~`重要~`經濟~`性~`魚種~。`俗稱~「`青~`甘~」、「`紅~`甘~」、「`油~`甘~」。"}],"A":"`（~鱼+师）","_":"3173800000","p":"shī","b":"ㄕ"}],"translation":{"francais":["Seriola qinqueradiata","queue jaune"],"English":["Seriola qinqueradiata","yellow tail"]}}