{"n":0,"t":"鼓","r":"`鼓~","c":13,"h":[{"d":[{"f":"`打擊樂器~`名~。`多~`為~`圓柱~`形~，`中~`空~，`兩端~`或~`一端~`蒙~`著~`皮革~，`以~`鼓槌~`敲擊~`鼓~`面~`發聲~。"},{"e":["例⃝「`一鼓作氣~」。"],"f":"`敲~`鼓~。"},{"e":["例⃝「`鼓掌~」。"],"f":"`敲~、`彈~`或~`拍~，`使~`發出~`聲響~。"},{"e":["例⃝「`鼓勵~」、「`鼓舞~」、「`鼓~`足~`幹勁~」。"],"f":"`振奮~；`激發~。"},{"e":["例⃝「`鼓~`風~」、「`鼓~`翅~`飛~`起~」、「`搖~`筆~`鼓舌~」、「`微風~`鼓~`浪~」。"],"f":"`振動~。"},{"e":["例⃝「`鼓鼓囊囊~」、「`肚子~`鼓~`起來~`了~」、「`她~`的~`眉頭~`蹙~`了~`起來~，`腮幫子~`也~`鼓~`了~`起來~」。"],"f":"`凸~`起~。"},{"e":["例⃝「`三~`鼓~`時分~，`狂風~`大作~」、「`剛~`過~`四~`鼓~，`菜場~`上~`已經~`熙熙攘攘~」。"],"f":"`古代~`夜間~`擊~`鼓~`報時~，`幾~`更~`也~`說~`幾~`鼓~。"},{"e":["例⃝「`石~`鼓~」、「`銅鼓~」、「`耳鼓~」、「`陣陣~`蛙~`鼓~`喧~」。"],"f":"`外形~、`聲音~`或~`作用~`像~`鼓~`的~`東西~。"},{"f":"`姓~。"},{"f":"`二~`一~`四部~`首~`之~`一~。"}],"_":"1047860000","p":"gǔ","b":"ㄍㄨˇ"}],"translation":{"francais":["tambour","bomber","207e radical"],"Deutsch":["Trommel  (S, Mus)","Radikal Nr. 207 = Trommel, trommeln, schlagen, Musik spielen, ermuntern, Luft hineinblasen "],"English":["drum","CL:`通~[tong4],`面~[mian4]","to drum","to strike","to rouse","to bulge","to swell"]}}